yaml_info/__init__.py
yaml_info/yamlinfo.py
YamlInfo-0.2.7.dist-info/LICENSE
YamlInfo-0.2.7.dist-info/METADATA
YamlInfo-0.2.7.dist-info/WHEEL
YamlInfo-0.2.7.dist-info/top_level.txt
YamlInfo-0.2.7.dist-info/RECORD
