Metadata-Version: 2.1
Name: YamlInfo
Version: 0.2.7
Summary: YamlInfo is a yaml config file parsing library intended to give custom functionality to parsing.
Home-page: https://github.com/AUCR/YamlInfo
Author: Wyatt Roersma
Author-email: wyatt@aucr.io
License: GPL-3.0
Platform: UNKNOWN
Classifier: Development Status :: 4 - Beta
Classifier: Intended Audience :: Developers
Classifier: License :: OSI Approved :: GNU General Public License v3 or later (GPLv3+)
Classifier: Programming Language :: Python :: 3.7
Requires-Dist: PyYAML
